README.rst
setup.py
findbak/__init__.py
findbak/findbak.py
findbak.egg-info/PKG-INFO
findbak.egg-info/SOURCES.txt
findbak.egg-info/dependency_links.txt
findbak.egg-info/entry_points.txt
findbak.egg-info/top_level.txt