Metadata-Version: 1.0
Name: findbak
Version: 0.1.1
Summary: File list backup
Home-page: https://github.com/spillevink/findbak
Author: Jakob Hedman
Author-email: jakob@hedman.email
License: GNU GPLv3
Platform: UNKNOWN
